smpclient/__init__.py
smpclient/exceptions.py
smpclient/extensions/__init__.py
smpclient/extensions/intercreate.py
smpclient/generics.py
smpclient/mcuboot.py
smpclient/py.typed
smpclient/requests/__init__.py
smpclient/requests/enumeration_management.py
smpclient/requests/file_management.py
smpclient/requests/image_management.py
smpclient/requests/os_management.py
smpclient/requests/settings_management.py
smpclient/requests/shell_management.py
smpclient/requests/statistics_management.py
smpclient/requests/user/__init__.py
smpclient/requests/user/intercreate.py
smpclient/requests/zephyr_management.py
smpclient/transport/__init__.py
smpclient/transport/_udp_client.py
smpclient/transport/ble.py
smpclient/transport/serial.py
smpclient/transport/udp.py
smpclient-6.1.0.dist-info/METADATA
smpclient-6.1.0.dist-info/WHEEL
smpclient-6.1.0.dist-info/entry_points.txt
smpclient-6.1.0.dist-info/licenses/LICENSE
smpclient-6.1.0.dist-info/RECORD
