Metadata-Version: 2.4
Name: smpclient
Version: 6.1.0
Summary: Simple Management Protocol (SMP) Client for remotely managing MCU firmware
License-Expression: Apache-2.0
License-File: LICENSE
Author: JP Hutchins
Author-email: jphutchins@gmail.com
Requires-Python: >=3.10,<4
Classifier: Development Status :: 5 - Production/Stable
Classifier: Intended Audience :: Developers
Classifier: License :: OSI Approved :: Apache Software License
Classifier: Programming Language :: Python
Classifier: Topic :: Software Development :: Libraries
Classifier: Framework :: AsyncIO
Classifier: Operating System :: Microsoft :: Windows
Classifier: Operating System :: POSIX :: Linux
Classifier: Operating System :: MacOS :: MacOS X
Requires-Dist: async-timeout (>=4.0.3,<5.0.0) ; python_version < "3.11"
Requires-Dist: bleak (>=2.0.0,<3.0.0)
Requires-Dist: intelhex (>=2.3.0,<3.0.0)
Requires-Dist: pyserial (>=3.5,<4.0)
Requires-Dist: smp (>=4.0.2,<5.0.0)
Project-URL: Documentation, https://intercreate.github.io/smpclient
Project-URL: Homepage, https://www.intercreate.io
Project-URL: Issues, https://github.com/intercreate/smpclient/issues
Project-URL: Repository, https://github.com/intercreate/smpclient.git
